utbpackage/__init__.py
utbpackage/utb_module.py
utb_test_package-0.2.0.dist-info/LICENSE
utb_test_package-0.2.0.dist-info/METADATA
utb_test_package-0.2.0.dist-info/WHEEL
utb_test_package-0.2.0.dist-info/top_level.txt
utb_test_package-0.2.0.dist-info/RECORD
