Metadata-Version: 2.1
Name: utb_test_package
Version: 0.2.0
Summary: Краткое описание вашего пакета
Home-page: https://github.com/utb404
Author: Artem Mikhaylov
Author-email: utb404@gmail.com
Classifier: Programming Language :: Python :: 3
Classifier: License :: OSI Approved :: MIT License
Requires-Python: >=3.6
License-File: LICENSE
